spice_api/__init__.py
spice_api/constants.py
spice_api/helpers.py
spice_api/objects.py
spice_api/spice.py
spice_api/stats.py
spice_api/tokens.py
spice_api-1.0.4.dist-info/DESCRIPTION.rst
spice_api-1.0.4.dist-info/METADATA
spice_api-1.0.4.dist-info/RECORD
spice_api-1.0.4.dist-info/WHEEL
spice_api-1.0.4.dist-info/metadata.json
spice_api-1.0.4.dist-info/top_level.txt
