Metadata-Version: 1.1
Name: spice_api
Version: 1.0.4
Summary: spice is a pure Python API that wraps around MALs Official API and makes it much better.
Home-page: https://github.com/Utagai/spice
Author: Mehrab Hoque
Author-email: mehrabhoque@gmail.com
License: MIT
Keywords: spice,MyAnimeList,API
Platform: UNKNOWN
Classifier: Development Status :: 4 - Beta
Classifier: Intended Audience :: Developers
Classifier: Topic :: Software Development :: Libraries :: Python Modules
Classifier: License :: OSI Approved :: MIT License
Classifier: Programming Language :: Python :: 2
Classifier: Programming Language :: Python :: 2.6
Classifier: Programming Language :: Python :: 2.7
Classifier: Programming Language :: Python :: 3
Classifier: Programming Language :: Python :: 3.3
Classifier: Programming Language :: Python :: 3.4
Classifier: Programming Language :: Python :: 3.5
